Workbook

Sheet TDS Summary
A1: TDS APPLICABILITY & THRESHOLD LIMITS – SECTIONS 194C, 194H, 194J, 194Q & 194I
A2: Applicable for FY 2026-27 (AY 2027-28). From 1 April 2026 these provisions are consolidated in s.393 of the Income-tax Act, 2025 (old section numbers retained here for reference). Thresholds/rates as amended up to Finance Act 2025.
A3: S.No | B3: Section (IT Act 1961) | C3: Nature of Payment | D3: Who deducts (Payer) | E3: Payee | F3: Threshold Limit (₹) | G3: TDS Rate – Individual/HUF payee | H3: TDS Rate – Other payee | I3: Rate if PAN not furnished (s.206AA) | J3: TDS deducted on | K3: Key Points / Remarks
A4: 1 | B4: 194C | C4: Payment to contractor / sub-contractor for carrying out any work (incl. supply of labour, advertising, catering, transport, job work) | D4: Any person other than Individual/HUF not liable to audit u/s 44AB; Govt., companies, firms, AOP, etc. | E4: Resident contractor / sub-contractor | F4: Single payment > ₹30,000 OR aggregate during FY > ₹1,00,000 | G4: 0.01 | H4: 0.02 | I4: 0.2 | J4: Full amount (once threshold is crossed) | K4: • Transporter owning ≤10 goods carriages and furnishing PAN: NIL TDS. • Contract for sale of goods is not covered; work contract is. • TDS on invoice value excluding GST if shown separately.
A5: 2 | B5: 194H | C5: Commission or brokerage (not being insurance commission u/s 194D) | D5: Individual/HUF liable to audit u/s 44AB and all other persons (other than individual/HUF not liable to audit) | E5: Resident person | F5: Aggregate during FY > ₹20,000 (raised from ₹15,000 w.e.f. 01.04.2025) | G5: 0.02 | H5: 0.02 | I5: 0.2 | J5: Full amount (once threshold is crossed) | K5: • Rate 2% w.e.f. 01.10.2024 (earlier 5%). • Not applicable on commission/brokerage to a principal-to-principal arrangement, or on securities-related brokerage per exceptions.
A6: 3 | B6: 194J(a) | C6: Fees for technical services, call-centre services, royalty for sale/distribution/exhibition of cinematographic films | D6: Any person other than Individual/HUF not liable to audit | E6: Resident person | F6: Aggregate during FY > ₹50,000 per category (raised from ₹30,000 w.e.f. 01.04.2025) | G6: 0.02 | H6: 0.02 | I6: 0.2 | J6: Full amount (once threshold is crossed) | K6: • Technical services ≠ managerial/consultancy services (those fall under 194J(b)). • Threshold is applied separately for each category of fee.
A7: 4 | B7: 194J(b) | C7: Fees for professional services, royalty (other than film royalty), non-compete fee, other sums u/s 28(va) | D7: Same as above | E7: Resident person | F7: Aggregate during FY > ₹50,000 per category | G7: 0.1 | H7: 0.1 | I7: 0.2 | J7: Full amount (once threshold is crossed) | K7: • Professionals: legal, medical, engineering, architecture, accountancy, interior decoration, etc. • Fee/remuneration to director (not salary) u/s 194J(1)(ba): 10%, NO threshold.
A8: 5 | B8: 194Q | C8: Purchase of goods from a resident seller | D8: Buyer whose turnover/gross receipts/sales > ₹10 crore in the immediately preceding FY | E8: Resident seller | F8: Aggregate purchases from a seller in FY > ₹50,00,000 | G8: 0.001 | H8: 0.001 | I8: 0.05 | J8: ONLY the amount exceeding ₹50 lakh | K8: • Threshold is per seller, cumulative from 1 April. • If seller has already charged TCS u/s 206C(1H), buyer has no TDS obligation on that transaction. • Not applicable where TDS applies under another section or 194-O (e-commerce). • GST shown separately in invoice is excluded from base (CBDT Circular 13/2021).
A9: 6 | B9: 194I(a) | C9: Rent of plant & machinery / equipment | D9: Any person other than Individual/HUF not liable to audit | E9: Resident person | F9: Aggregate rent during FY > ₹6,00,000 (raised from ₹2,40,000 w.e.f. 01.04.2025) | G9: 0.02 | H9: 0.02 | I9: 0.2 | J9: Full amount (once threshold is crossed) | K9: • Covers rent under lease, sub-lease, tenancy or any agreement. • Threshold applies per payee (landlord) per FY.
A10: 7 | B10: 194I(b) | C10: Rent of land, building (incl. factory building) or furniture / fittings | D10: Any person other than Individual/HUF not liable to audit | E10: Resident person | F10: Aggregate rent during FY > ₹6,00,000 | G10: 0.1 | H10: 0.1 | I10: 0.2 | J10: Full amount (once threshold is crossed) | K10: • Individual/HUF not liable to audit paying rent > ₹50,000 per month: s.194-IB at 2% (deducted once, in last month of tenancy/FY). • GST on rent: if shown separately, excluded from base.

Sheet Rate Master
A1: RATE & THRESHOLD MASTER (edit blue cells if law changes)
A2: Blue = hardcoded inputs taken from the TDS Summary sheet. The Calculator reads from this table.
A4: Key | B4: Section | C4: Single payment threshold (₹) (0 = n/a) | D4: Annual / aggregate threshold (₹) | E4: Rate – Individual/HUF | F4: Rate – Others | G4: Rate – No PAN | H4: Base
A5: 194C – Contractor | B5: 194C | C5: 30000 | D5: 100000 | E5: 0.01 | F5: 0.02 | G5: 0.2 | H5: Full
A6: 194H – Commission/Brokerage | B6: 194H | C6: 0 | D6: 20000 | E6: 0.02 | F6: 0.02 | G6: 0.2 | H6: Full
A7: 194J(a) – Technical services/Call centre | B7: 194J | C7: 0 | D7: 50000 | E7: 0.02 | F7: 0.02 | G7: 0.2 | H7: Full
A8: 194J(b) – Professional fees/Royalty/Non-compete | B8: 194J | C8: 0 | D8: 50000 | E8: 0.1 | F8: 0.1 | G8: 0.2 | H8: Full
A9: 194J(ba) – Director remuneration | B9: 194J | C9: 0 | D9: 0 | E9: 0.1 | F9: 0.1 | G9: 0.2 | H9: Full
A10: 194Q – Purchase of goods | B10: 194Q | C10: 0 | D10: 5000000 | E10: 0.001 | F10: 0.001 | G10: 0.05 | H10: Excess
A11: 194I(a) – Rent: Plant & Machinery | B11: 194I | C11: 0 | D11: 600000 | E11: 0.02 | F11: 0.02 | G11: 0.2 | H11: Full
A12: 194I(b) – Rent: Land/Building/Furniture | B12: 194I | C12: 0 | D12: 600000 | E12: 0.1 | F12: 0.1 | G12: 0.2 | H12: Full
A14: Base: 'Full' = TDS on entire aggregate once threshold exceeded; 'Excess' = TDS only on amount above threshold (194Q).

Sheet Applicability Checker
A1: TDS APPLICABILITY CHECKER
A2: Yellow cells = inputs (row 5 is an example – overwrite it). Grey columns calculate automatically from the Rate Master. Amounts should exclude GST where GST is shown separately.
A4: Party / Payee name | B4: Nature of payment (select) | C4: Payee type (select) | D4: PAN available? (select) | E4: Single payment (₹) | F4: Aggregate payments in FY incl. current (₹) | G4: Threshold crossed? | H4: TDS base (₹) | I4: TDS rate applied | J4: TDS amount (₹)
A5: ABC Contractors | B5: 194C – Contractor | C5: Other | D5: Yes | E5: 45000 | F5: 120000 | G5: =IF($B5="","",IF(OR(AND(INDEX('Rate Master'!$C$5:$C$12,MATCH($B5,'Rate Master'!$A$5:$A$12,0))>0,$E5>INDEX('Rate Master'!$C$5:$C$12,MATCH($B5,'Rate Master'!$A$5:$A$12,0))),$F5>INDEX('Rate Master'!$D$5:$D$12,MATCH($B5,'Rate Master'!$A$5:$A$12,0))),"Yes – deduct TDS","No – below threshold")) -> Yes – deduct TDS | H5: =IF(LEFT($G5,3)<>"Yes",0,IF(INDEX('Rate Master'!$H$5:$H$12,MATCH($B5,'Rate Master'!$A$5:$A$12,0))="Excess",MAX(0,$F5-INDEX('Rate Master'!$D$5:$D$12,MATCH($B5,'Rate Master'!$A$5:$A$12,0))),$F5)) -> 120000 | I5: =IF($B5="","",IF($D5="No",MAX(INDEX('Rate Master'!$G$5:$G$12,MATCH($B5,'Rate Master'!$A$5:$A$12,0)),IF($C5="Individual/HUF",INDEX('Rate Master'!$E$5:$E$12,MATCH($B5,'Rate Master'!$A$5:$A$12,0)),INDEX('Rate Master'!$F$5:$F$12,MATCH($B5,'Rate Master'!$A$5:$A$12,0)))),IF($C5="Individual/HUF",INDEX('Rate Master'!$E$5:$E$12,MATCH($B5,'Rate Master'!$A$5:$A$12,0)),INDEX('Rate Master'!$F$5:$F$12,MATCH($B5,'Rate Master'!$A$5:$A$12,0))))) -> 0.02 | J5: =IF($B5="",0,ROUND($H5*$I5,0)) -> 2400
G6: =IF($B6="","",IF(OR(AND(INDEX('Rate Master'!$C$5:$C$12,MATCH($B6,'Rate Master'!$A$5:$A$12,0))>0,$E6>INDEX('Rate Master'!$C$5:$C$12,MATCH($B6,'Rate Master'!$A$5:$A$12,0))),$F6>INDEX('Rate Master'!$D$5:$D$12,MATCH($B6,'Rate Master'!$A$5:$A$12,0))),"Yes – deduct TDS","No – below threshold")) | H6: =IF(LEFT($G6,3)<>"Yes",0,IF(INDEX('Rate Master'!$H$5:$H$12,MATCH($B6,'Rate Master'!$A$5:$A$12,0))="Excess",MAX(0,$F6-INDEX('Rate Master'!$D$5:$D$12,MATCH($B6,'Rate Master'!$A$5:$A$12,0))),$F6)) -> 0 | I6: =IF($B6="","",IF($D6="No",MAX(INDEX('Rate Master'!$G$5:$G$12,MATCH($B6,'Rate Master'!$A$5:$A$12,0)),IF($C6="Individual/HUF",INDEX('Rate Master'!$E$5:$E$12,MATCH($B6,'Rate Master'!$A$5:$A$12,0)),INDEX('Rate Master'!$F$5:$F$12,MATCH($B6,'Rate Master'!$A$5:$A$12,0)))),IF($C6="Individual/HUF",INDEX('Rate Master'!$E$5:$E$12,MATCH($B6,'Rate Master'!$A$5:$A$12,0)),INDEX('Rate Master'!$F$5:$F$12,MATCH($B6,'Rate Master'!$A$5:$A$12,0))))) | J6: =IF($B6="",0,ROUND($H6*$I6,0)) -> 0
G7: =IF($B7="","",IF(OR(AND(INDEX('Rate Master'!$C$5:$C$12,MATCH($B7,'Rate Master'!$A$5:$A$12,0))>0,$E7>INDEX('Rate Master'!$C$5:$C$12,MATCH($B7,'Rate Master'!$A$5:$A$12,0))),$F7>INDEX('Rate Master'!$D$5:$D$12,MATCH($B7,'Rate Master'!$A$5:$A$12,0))),"Yes – deduct TDS","No – below threshold")) | H7: =IF(LEFT($G7,3)<>"Yes",0,IF(INDEX('Rate Master'!$H$5:$H$12,MATCH($B7,'Rate Master'!$A$5:$A$12,0))="Excess",MAX(0,$F7-INDEX('Rate Master'!$D$5:$D$12,MATCH($B7,'Rate Master'!$A$5:$A$12,0))),$F7)) -> 0 | I7: =IF($B7="","",IF($D7="No",MAX(INDEX('Rate Master'!$G$5:$G$12,MATCH($B7,'Rate Master'!$A$5:$A$12,0)),IF($C7="Individual/HUF",INDEX('Rate Master'!$E$5:$E$12,MATCH($B7,'Rate Master'!$A$5:$A$12,0)),INDEX('Rate Master'!$F$5:$F$12,MATCH($B7,'Rate Master'!$A$5:$A$12,0)))),IF($C7="Individual/HUF",INDEX('Rate Master'!$E$5:$E$12,MATCH($B7,'Rate Master'!$A$5:$A$12,0)),INDEX('Rate Master'!$F$5:$F$12,MATCH($B7,'Rate Master'!$A$5:$A$12,0))))) | J7: =IF($B7="",0,ROUND($H7*$I7,0)) -> 0
G8: =IF($B8="","",IF(OR(AND(INDEX('Rate Master'!$C$5:$C$12,MATCH($B8,'Rate Master'!$A$5:$A$12,0))>0,$E8>INDEX('Rate Master'!$C$5:$C$12,MATCH($B8,'Rate Master'!$A$5:$A$12,0))),$F8>INDEX('Rate Master'!$D$5:$D$12,MATCH($B8,'Rate Master'!$A$5:$A$12,0))),"Yes – deduct TDS","No – below threshold")) | H8: =IF(LEFT($G8,3)<>"Yes",0,IF(INDEX('Rate Master'!$H$5:$H$12,MATCH($B8,'Rate Master'!$A$5:$A$12,0))="Excess",MAX(0,$F8-INDEX('Rate Master'!$D$5:$D$12,MATCH($B8,'Rate Master'!$A$5:$A$12,0))),$F8)) -> 0 | I8: =IF($B8="","",IF($D8="No",MAX(INDEX('Rate Master'!$G$5:$G$12,MATCH($B8,'Rate Master'!$A$5:$A$12,0)),IF($C8="Individual/HUF",INDEX('Rate Master'!$E$5:$E$12,MATCH($B8,'Rate Master'!$A$5:$A$12,0)),INDEX('Rate Master'!$F$5:$F$12,MATCH($B8,'Rate Master'!$A$5:$A$12,0)))),IF($C8="Individual/HUF",INDEX('Rate Master'!$E$5:$E$12,MATCH($B8,'Rate Master'!$A$5:$A$12,0)),INDEX('Rate Master'!$F$5:$F$12,MATCH($B8,'Rate Master'!$A$5:$A$12,0))))) | J8: =IF($B8="",0,ROUND($H8*$I8,0)) -> 0
G9: =IF($B9="","",IF(OR(AND(INDEX('Rate Master'!$C$5:$C$12,MATCH($B9,'Rate Master'!$A$5:$A$12,0))>0,$E9>INDEX('Rate Master'!$C$5:$C$12,MATCH($B9,'Rate Master'!$A$5:$A$12,0))),$F9>INDEX('Rate Master'!$D$5:$D$12,MATCH($B9,'Rate Master'!$A$5:$A$12,0))),"Yes – deduct TDS","No – below threshold")) | H9: =IF(LEFT($G9,3)<>"Yes",0,IF(INDEX('Rate Master'!$H$5:$H$12,MATCH($B9,'Rate Master'!$A$5:$A$12,0))="Excess",MAX(0,$F9-INDEX('Rate Master'!$D$5:$D$12,MATCH($B9,'Rate Master'!$A$5:$A$12,0))),$F9)) -> 0 | I9: =IF($B9="","",IF($D9="No",MAX(INDEX('Rate Master'!$G$5:$G$12,MATCH($B9,'Rate Master'!$A$5:$A$12,0)),IF($C9="Individual/HUF",INDEX('Rate Master'!$E$5:$E$12,MATCH($B9,'Rate Master'!$A$5:$A$12,0)),INDEX('Rate Master'!$F$5:$F$12,MATCH($B9,'Rate Master'!$A$5:$A$12,0)))),IF($C9="Individual/HUF",INDEX('Rate Master'!$E$5:$E$12,MATCH($B9,'Rate Master'!$A$5:$A$12,0)),INDEX('Rate Master'!$F$5:$F$12,MATCH($B9,'Rate Master'!$A$5:$A$12,0))))) | J9: =IF($B9="",0,ROUND($H9*$I9,0)) -> 0
G10: =IF($B10="","",IF(OR(AND(INDEX('Rate Master'!$C$5:$C$12,MATCH($B10,'Rate Master'!$A$5:$A$12,0))>0,$E10>INDEX('Rate Master'!$C$5:$C$12,MATCH($B10,'Rate Master'!$A$5:$A$12,0))),$F10>INDEX('Rate Master'!$D$5:$D$12,MATCH($B10,'Rate Master'!$A$5:$A$12,0))),"Yes – deduct TDS","No – below threshold")) | H10: =IF(LEFT($G10,3)<>"Yes",0,IF(INDEX('Rate Master'!$H$5:$H$12,MATCH($B10,'Rate Master'!$A$5:$A$12,0))="Excess",MAX(0,$F10-INDEX('Rate Master'!$D$5:$D$12,MATCH($B10,'Rate Master'!$A$5:$A$12,0))),$F10)) -> 0 | I10: =IF($B10="","",IF($D10="No",MAX(INDEX('Rate Master'!$G$5:$G$12,MATCH($B10,'Rate Master'!$A$5:$A$12,0)),IF($C10="Individual/HUF",INDEX('Rate Master'!$E$5:$E$12,MATCH($B10,'Rate Master'!$A$5:$A$12,0)),INDEX('Rate Master'!$F$5:$F$12,MATCH($B10,'Rate Master'!$A$5:$A$12,0)))),IF($C10="Individual/HUF",INDEX('Rate Master'!$E$5:$E$12,MATCH($B10,'Rate Master'!$A$5:$A$12,0)),INDEX('Rate Master'!$F$5:$F$12,MATCH($B10,'Rate Master'!$A$5:$A$12,0))))) | J10: =IF($B10="",0,ROUND($H10*$I10,0)) -> 0
G11: =IF($B11="","",IF(OR(AND(INDEX('Rate Master'!$C$5:$C$12,MATCH($B11,'Rate Master'!$A$5:$A$12,0))>0,$E11>INDEX('Rate Master'!$C$5:$C$12,MATCH($B11,'Rate Master'!$A$5:$A$12,0))),$F11>INDEX('Rate Master'!$D$5:$D$12,MATCH($B11,'Rate Master'!$A$5:$A$12,0))),"Yes – deduct TDS","No – below threshold")) | H11: =IF(LEFT($G11,3)<>"Yes",0,IF(INDEX('Rate Master'!$H$5:$H$12,MATCH($B11,'Rate Master'!$A$5:$A$12,0))="Excess",MAX(0,$F11-INDEX('Rate Master'!$D$5:$D$12,MATCH($B11,'Rate Master'!$A$5:$A$12,0))),$F11)) -> 0 | I11: =IF($B11="","",IF($D11="No",MAX(INDEX('Rate Master'!$G$5:$G$12,MATCH($B11,'Rate Master'!$A$5:$A$12,0)),IF($C11="Individual/HUF",INDEX('Rate Master'!$E$5:$E$12,MATCH($B11,'Rate Master'!$A$5:$A$12,0)),INDEX('Rate Master'!$F$5:$F$12,MATCH($B11,'Rate Master'!$A$5:$A$12,0)))),IF($C11="Individual/HUF",INDEX('Rate Master'!$E$5:$E$12,MATCH($B11,'Rate Master'!$A$5:$A$12,0)),INDEX('Rate Master'!$F$5:$F$12,MATCH($B11,'Rate Master'!$A$5:$A$12,0))))) | J11: =IF($B11="",0,ROUND($H11*$I11,0)) -> 0
G12: =IF($B12="","",IF(OR(AND(INDEX('Rate Master'!$C$5:$C$12,MATCH($B12,'Rate Master'!$A$5:$A$12,0))>0,$E12>INDEX('Rate Master'!$C$5:$C$12,MATCH($B12,'Rate Master'!$A$5:$A$12,0))),$F12>INDEX('Rate Master'!$D$5:$D$12,MATCH($B12,'Rate Master'!$A$5:$A$12,0))),"Yes – deduct TDS","No – below threshold")) | H12: =IF(LEFT($G12,3)<>"Yes",0,IF(INDEX('Rate Master'!$H$5:$H$12,MATCH($B12,'Rate Master'!$A$5:$A$12,0))="Excess",MAX(0,$F12-INDEX('Rate Master'!$D$5:$D$12,MATCH($B12,'Rate Master'!$A$5:$A$12,0))),$F12)) -> 0 | I12: =IF($B12="","",IF($D12="No",MAX(INDEX('Rate Master'!$G$5:$G$12,MATCH($B12,'Rate Master'!$A$5:$A$12,0)),IF($C12="Individual/HUF",INDEX('Rate Master'!$E$5:$E$12,MATCH($B12,'Rate Master'!$A$5:$A$12,0)),INDEX('Rate Master'!$F$5:$F$12,MATCH($B12,'Rate Master'!$A$5:$A$12,0)))),IF($C12="Individual/HUF",INDEX('Rate Master'!$E$5:$E$12,MATCH($B12,'Rate Master'!$A$5:$A$12,0)),INDEX('Rate Master'!$F$5:$F$12,MATCH($B12,'Rate Master'!$A$5:$A$12,0))))) | J12: =IF($B12="",0,ROUND($H12*$I12,0)) -> 0
G13: =IF($B13="","",IF(OR(AND(INDEX('Rate Master'!$C$5:$C$12,MATCH($B13,'Rate Master'!$A$5:$A$12,0))>0,$E13>INDEX('Rate Master'!$C$5:$C$12,MATCH($B13,'Rate Master'!$A$5:$A$12,0))),$F13>INDEX('Rate Master'!$D$5:$D$12,MATCH($B13,'Rate Master'!$A$5:$A$12,0))),"Yes – deduct TDS","No – below threshold")) | H13: =IF(LEFT($G13,3)<>"Yes",0,IF(INDEX('Rate Master'!$H$5:$H$12,MATCH($B13,'Rate Master'!$A$5:$A$12,0))="Excess",MAX(0,$F13-INDEX('Rate Master'!$D$5:$D$12,MATCH($B13,'Rate Master'!$A$5:$A$12,0))),$F13)) -> 0 | I13: =IF($B13="","",IF($D13="No",MAX(INDEX('Rate Master'!$G$5:$G$12,MATCH($B13,'Rate Master'!$A$5:$A$12,0)),IF($C13="Individual/HUF",INDEX('Rate Master'!$E$5:$E$12,MATCH($B13,'Rate Master'!$A$5:$A$12,0)),INDEX('Rate Master'!$F$5:$F$12,MATCH($B13,'Rate Master'!$A$5:$A$12,0)))),IF($C13="Individual/HUF",INDEX('Rate Master'!$E$5:$E$12,MATCH($B13,'Rate Master'!$A$5:$A$12,0)),INDEX('Rate Master'!$F$5:$F$12,MATCH($B13,'Rate Master'!$A$5:$A$12,0))))) | J13: =IF($B13="",0,ROUND($H13*$I13,0)) -> 0
G14: =IF($B14="","",IF(OR(AND(INDEX('Rate Master'!$C$5:$C$12,MATCH($B14,'Rate Master'!$A$5:$A$12,0))>0,$E14>INDEX('Rate Master'!$C$5:$C$12,MATCH($B14,'Rate Master'!$A$5:$A$12,0))),$F14>INDEX('Rate Master'!$D$5:$D$12,MATCH($B14,'Rate Master'!$A$5:$A$12,0))),"Yes – deduct TDS","No – below threshold")) | H14: =IF(LEFT($G14,3)<>"Yes",0,IF(INDEX('Rate Master'!$H$5:$H$12,MATCH($B14,'Rate Master'!$A$5:$A$12,0))="Excess",MAX(0,$F14-INDEX('Rate Master'!$D$5:$D$12,MATCH($B14,'Rate Master'!$A$5:$A$12,0))),$F14)) -> 0 | I14: =IF($B14="","",IF($D14="No",MAX(INDEX('Rate Master'!$G$5:$G$12,MATCH($B14,'Rate Master'!$A$5:$A$12,0)),IF($C14="Individual/HUF",INDEX('Rate Master'!$E$5:$E$12,MATCH($B14,'Rate Master'!$A$5:$A$12,0)),INDEX('Rate Master'!$F$5:$F$12,MATCH($B14,'Rate Master'!$A$5:$A$12,0)))),IF($C14="Individual/HUF",INDEX('Rate Master'!$E$5:$E$12,MATCH($B14,'Rate Master'!$A$5:$A$12,0)),INDEX('Rate Master'!$F$5:$F$12,MATCH($B14,'Rate Master'!$A$5:$A$12,0))))) | J14: =IF($B14="",0,ROUND($H14*$I14,0)) -> 0
G15: =IF($B15="","",IF(OR(AND(INDEX('Rate Master'!$C$5:$C$12,MATCH($B15,'Rate Master'!$A$5:$A$12,0))>0,$E15>INDEX('Rate Master'!$C$5:$C$12,MATCH($B15,'Rate Master'!$A$5:$A$12,0))),$F15>INDEX('Rate Master'!$D$5:$D$12,MATCH($B15,'Rate Master'!$A$5:$A$12,0))),"Yes – deduct TDS","No – below threshold")) | H15: =IF(LEFT($G15,3)<>"Yes",0,IF(INDEX('Rate Master'!$H$5:$H$12,MATCH($B15,'Rate Master'!$A$5:$A$12,0))="Excess",MAX(0,$F15-INDEX('Rate Master'!$D$5:$D$12,MATCH($B15,'Rate Master'!$A$5:$A$12,0))),$F15)) -> 0 | I15: =IF($B15="","",IF($D15="No",MAX(INDEX('Rate Master'!$G$5:$G$12,MATCH($B15,'Rate Master'!$A$5:$A$12,0)),IF($C15="Individual/HUF",INDEX('Rate Master'!$E$5:$E$12,MATCH($B15,'Rate Master'!$A$5:$A$12,0)),INDEX('Rate Master'!$F$5:$F$12,MATCH($B15,'Rate Master'!$A$5:$A$12,0)))),IF($C15="Individual/HUF",INDEX('Rate Master'!$E$5:$E$12,MATCH($B15,'Rate Master'!$A$5:$A$12,0)),INDEX('Rate Master'!$F$5:$F$12,MATCH($B15,'Rate Master'!$A$5:$A$12,0))))) | J15: =IF($B15="",0,ROUND($H15*$I15,0)) -> 0
G16: =IF($B16="","",IF(OR(AND(INDEX('Rate Master'!$C$5:$C$12,MATCH($B16,'Rate Master'!$A$5:$A$12,0))>0,$E16>INDEX('Rate Master'!$C$5:$C$12,MATCH($B16,'Rate Master'!$A$5:$A$12,0))),$F16>INDEX('Rate Master'!$D$5:$D$12,MATCH($B16,'Rate Master'!$A$5:$A$12,0))),"Yes – deduct TDS","No – below threshold")) | H16: =IF(LEFT($G16,3)<>"Yes",0,IF(INDEX('Rate Master'!$H$5:$H$12,MATCH($B16,'Rate Master'!$A$5:$A$12,0))="Excess",MAX(0,$F16-INDEX('Rate Master'!$D$5:$D$12,MATCH($B16,'Rate Master'!$A$5:$A$12,0))),$F16)) -> 0 | I16: =IF($B16="","",IF($D16="No",MAX(INDEX('Rate Master'!$G$5:$G$12,MATCH($B16,'Rate Master'!$A$5:$A$12,0)),IF($C16="Individual/HUF",INDEX('Rate Master'!$E$5:$E$12,MATCH($B16,'Rate Master'!$A$5:$A$12,0)),INDEX('Rate Master'!$F$5:$F$12,MATCH($B16,'Rate Master'!$A$5:$A$12,0)))),IF($C16="Individual/HUF",INDEX('Rate Master'!$E$5:$E$12,MATCH($B16,'Rate Master'!$A$5:$A$12,0)),INDEX('Rate Master'!$F$5:$F$12,MATCH($B16,'Rate Master'!$A$5:$A$12,0))))) | J16: =IF($B16="",0,ROUND($H16*$I16,0)) -> 0
G17: =IF($B17="","",IF(OR(AND(INDEX('Rate Master'!$C$5:$C$12,MATCH($B17,'Rate Master'!$A$5:$A$12,0))>0,$E17>INDEX('Rate Master'!$C$5:$C$12,MATCH($B17,'Rate Master'!$A$5:$A$12,0))),$F17>INDEX('Rate Master'!$D$5:$D$12,MATCH($B17,'Rate Master'!$A$5:$A$12,0))),"Yes – deduct TDS","No – below threshold")) | H17: =IF(LEFT($G17,3)<>"Yes",0,IF(INDEX('Rate Master'!$H$5:$H$12,MATCH($B17,'Rate Master'!$A$5:$A$12,0))="Excess",MAX(0,$F17-INDEX('Rate Master'!$D$5:$D$12,MATCH($B17,'Rate Master'!$A$5:$A$12,0))),$F17)) -> 0 | I17: =IF($B17="","",IF($D17="No",MAX(INDEX('Rate Master'!$G$5:$G$12,MATCH($B17,'Rate Master'!$A$5:$A$12,0)),IF($C17="Individual/HUF",INDEX('Rate Master'!$E$5:$E$12,MATCH($B17,'Rate Master'!$A$5:$A$12,0)),INDEX('Rate Master'!$F$5:$F$12,MATCH($B17,'Rate Master'!$A$5:$A$12,0)))),IF($C17="Individual/HUF",INDEX('Rate Master'!$E$5:$E$12,MATCH($B17,'Rate Master'!$A$5:$A$12,0)),INDEX('Rate Master'!$F$5:$F$12,MATCH($B17,'Rate Master'!$A$5:$A$12,0))))) | J17: =IF($B17="",0,ROUND($H17*$I17,0)) -> 0
... G34: =IF($B34="","",IF(OR(AND(INDEX('Rate Master'!$C$5:$C$12,MATCH($B34,'Rate Master'!$A$5:$A$12,0))>0,$E34>INDEX('Rate Master'!$C$5:$C$12,MATCH($B34,'Rate Master'!$A$5:$A$12,0))),$F34>INDEX('Rate Master'!$D$5:$D$12,MATCH($B34,'Rate Master'!$A$5:$A$12,0))),"Yes – deduct TDS","No – below threshold")) | H34: =IF(LEFT($G34,3)<>"Yes",0,IF(INDEX('Rate Master'!$H$5:$H$12,MATCH($B34,'Rate Master'!$A$5:$A$12,0))="Excess",MAX(0,$F34-INDEX('Rate Master'!$D$5:$D$12,MATCH($B34,'Rate Master'!$A$5:$A$12,0))),$F34)) -> 0 | I34: =IF($B34="","",IF($D34="No",MAX(INDEX('Rate Master'!$G$5:$G$12,MATCH($B34,'Rate Master'!$A$5:$A$12,0)),IF($C34="Individual/HUF",INDEX('Rate Master'!$E$5:$E$12,MATCH($B34,'Rate Master'!$A$5:$A$12,0)),INDEX('Rate Master'!$F$5:$F$12,MATCH($B34,'Rate Master'!$A$5:$A$12,0)))),IF($C34="Individual/HUF",INDEX('Rate Master'!$E$5:$E$12,MATCH($B34,'Rate Master'!$A$5:$A$12,0)),INDEX('Rate Master'!$F$5:$F$12,MATCH($B34,'Rate Master'!$A$5:$A$12,0))))) | J34: =IF($B34="",0,ROUND($H34*$I34,0)) -> 0
I35: Total TDS | J35: =SUM(J5:J34) -> 2400
A37: Legend: Yellow = input | Grey = formula. Where no PAN is furnished, higher of normal rate and s.206AA rate is applied (20%; 5% for 194Q). Aggregate threshold for 194C is tested against both single-payment (₹30,000) and aggregate (₹1,00,000) limits.

Sheet Compliance & Penalties
A1: COMPLIANCE CALENDAR & CONSEQUENCES OF DEFAULT
A2: General reference – confirm due dates against the latest CBDT notifications.
A4: Item | B4: Detail | C4: Applies to
A5: Time of deduction | B5: Earlier of credit to payee's account or actual payment (cash/cheque/draft/other mode). | C5: 194C, 194H, 194J, 194I, 194Q
A6: Deposit of TDS | B6: By 7th of the following month; for March deductions by 30th April (Govt. deductors without challan: same day). | C6: All
A7: Quarterly TDS return | B7: Form 26Q: Q1 – 31 Jul, Q2 – 31 Oct, Q3 – 31 Jan, Q4 – 31 May. (Form numbers under the 2025 Act may differ – check portal.) | C7: All
A8: TDS certificate | B8: Form 16A within 15 days of the due date of filing the quarterly return. | C8: All
A9: Interest – late deduction | B9: 1% per month or part of month from date tax was deductible to date of deduction. | C9: All
A10: Interest – late deposit | B10: 1.5% per month or part of month from date of deduction to date of deposit. | C10: All
A11: Late fee on return | B11: ₹200 per day u/s 234E (capped at the TDS amount). | C11: All
A12: Penalty | B12: s.271C – penalty equal to amount of TDS not deducted/deposited; s.271H – ₹10,000 to ₹1,00,000 for return default. | C12: All
A13: Disallowance of expense | B13: 30% of the expenditure disallowed u/s 40(a)(ia) if TDS not deducted/deposited (allowed in the year of deposit). | C13: 194C, 194H, 194J, 194I (and 194Q)
A14: Lower / nil deduction | B14: Certificate u/s 197 from the Assessing Officer; Form 15G/15H not available for these payments. | C14: All
A15: Non-filer higher rate (s.206AB) | B15: Omitted w.e.f. 01.04.2025 – no longer applicable. | C15: All
